{
  "$defs": {
    "content": {
      "@type": "sb-ed:Content",
      "identifier": "identifier",
      "name": "name",
      "status": "status",
      "channel": "channel",
      "publishedOn": "lastPublishedOn",
      "primaryCategory": "primaryCategory"
    },
    "collection": {
      "@type": "sb-ed:Collection",
      "identifier": "identifier",
      "name": "name",
      "status": "status",
      "channel": "channel",
      "published On": "lastPublishedOn",
      "primary Category": "primaryCategory",
      "license": "license"
    },
    "collectionUnit": {
      "@type": "sb-ed:CollectionUnit",
      "identifier": "identifier",
      "name": "name"
    },
    "framework": {
      "@type": "sb-ed:Framework",
      "identifier": "framework",
      "board": "board",
      "medium": "medium",
      "class": "gradeLevel",
      "subject": "subject",
      "topic": "topic",
      "learningOutcome": "learningOutcome",
      "purpose": "purpose"
    }
  },
  "digital_textbook": {
    "@type": "sb-ed:TextBook",
    "$ref": "#/$defs/collection",
    "framework" : { "$ref" : "#/$defs/framework" }
  },
  "textbook_unit": {
    "@type": "sb-ed:TextBookUnit",
    "$ref": "#/$defs/collectionUnit",
    "parentInfo": {"$ref": "#/digital_textbook"}
  },
  "course": {
    "@type": "sb-ed:Course",
    "$ref": "#/$defs/collection",
    "framework": { "$ref" : "#/$defs/framework" }
  },
  "course_unit": {
    "@type": "sb-ed:CourseUnit",
    "$ref": "#/$defs/collectionUnit",
    "parentInfo": {"$ref": "#/course" }
  }
}